sqlmesh_dag_generator/__init__.py
sqlmesh_dag_generator/airflow_utils.py
sqlmesh_dag_generator/cli.py
sqlmesh_dag_generator/config.py
sqlmesh_dag_generator/dag_builder.py
sqlmesh_dag_generator/generator.py
sqlmesh_dag_generator/models.py
sqlmesh_dag_generator/security.py
sqlmesh_dag_generator/utils.py
sqlmesh_dag_generator/validation.py
sqlmesh_dag_generator-0.9.0.dist-info/licenses/LICENSE
sqlmesh_dag_generator-0.9.0.dist-info/METADATA
sqlmesh_dag_generator-0.9.0.dist-info/WHEEL
sqlmesh_dag_generator-0.9.0.dist-info/entry_points.txt
sqlmesh_dag_generator-0.9.0.dist-info/top_level.txt
sqlmesh_dag_generator-0.9.0.dist-info/RECORD
