Metadata-Version: 2.4
Name: sqlmesh-dag-generator
Version: 0.9.0
Summary: Open-source Airflow DAG generator for SQLMesh projects
Home-page: https://github.com/kubolko/sqlmesh-dag-generator
Author: Jakub Sumionka
Author-email: jakub.sumionka@gmail.com
Project-URL: Bug Reports, https://github.com/kubolko/sqlmesh-dag-generator/issues
Project-URL: Source, https://github.com/kubolko/sqlmesh-dag-generator
Project-URL: Documentation, https://github.com/kubolko/sqlmesh-dag-generator/docs
Keywords: sqlmesh airflow dag generator etl data-engineering
Classifier: Development Status :: 3 - Alpha
Classifier: Intended Audience :: Developers
Classifier: Topic :: Software Development :: Code Generators
Classifier: License :: OSI Approved :: MIT License
Classifier: Programming Language :: Python :: 3
Classifier: Programming Language :: Python :: 3.8
Classifier: Programming Language :: Python :: 3.9
Classifier: Programming Language :: Python :: 3.10
Classifier: Programming Language :: Python :: 3.11
Classifier: Programming Language :: Python :: 3.12
Requires-Python: >=3.8
License-File: LICENSE
Provides-Extra: dev
Requires-Dist: pytest>=7.0.0; extra == "dev"
Requires-Dist: pytest-cov>=4.0.0; extra == "dev"
Requires-Dist: black>=23.0.0; extra == "dev"
Requires-Dist: ruff>=0.1.0; extra == "dev"
Requires-Dist: mypy>=1.0.0; extra == "dev"
Dynamic: author
Dynamic: author-email
Dynamic: classifier
Dynamic: description
Dynamic: description-content-type
Dynamic: home-page
Dynamic: keywords
Dynamic: license-file
Dynamic: project-url
Dynamic: provides-extra
Dynamic: requires-python
Dynamic: summary
